[
  {
    "id": "getData.0",
    "status": "FAILED",
    "error": {}
  },
  {
    "id": "setDataWithLargeArgs.0",
    "status": "SUCCEED",
    "data": "foo"
  },
  {
    "id": "localVarMethod.0",
    "status": "SUCCEED",
    "data": true
  },
  {
    "id": "setDataWithMany.0",
    "status": "SUCCEED",
    "data": "ABCDEFGHIJKL"
  },
  {
    "id": "setDataWithManyStructuredArgs.0",
    "status": "SUCCEED",
    "data": true
  },
  {
    "id": "globalVarMethod.0",
    "status": "SUCCEED",
    "data": true
  },
  {
    "id": "subsequentInvokes.0",
    "status": "SUCCEED",
    "data": [
      "77"
    ]
  }
]